vectara_client/__init__.py
vectara_client/api_client.py
vectara_client/api_response.py
vectara_client/auth.py
vectara_client/config.py
vectara_client/configuration.py
vectara_client/core.py
vectara_client/corpus.py
vectara_client/documents.py
vectara_client/exceptions.py
vectara_client/our_rest.py
vectara_client/py.typed
vectara_client/rest.py
vectara_client/util.py
vectara_client/api/__init__.py
vectara_client/api/api_keys_api.py
vectara_client/api/application_clients_api.py
vectara_client/api/chats_api.py
vectara_client/api/corpora_api.py
vectara_client/api/documents_api.py
vectara_client/api/encoders_api.py
vectara_client/api/index_api.py
vectara_client/api/jobs_api.py
vectara_client/api/large_language_models_api.py
vectara_client/api/queries_api.py
vectara_client/api/rerankers_api.py
vectara_client/api/upload_api.py
vectara_client/api/users_api.py
vectara_client/models/__init__.py
vectara_client/models/api_key.py
vectara_client/models/api_key_role.py
vectara_client/models/api_operation_policy.py
vectara_client/models/api_policy.py
vectara_client/models/api_role.py
vectara_client/models/app_client.py
vectara_client/models/bad_request_error.py
vectara_client/models/chat.py
vectara_client/models/chat_full_response.py
vectara_client/models/chat_info_response.py
vectara_client/models/chat_parameters.py
vectara_client/models/chat_request.py
vectara_client/models/chat_streamed_response.py
vectara_client/models/citation_parameters.py
vectara_client/models/context_configuration.py
vectara_client/models/core_document.py
vectara_client/models/core_document_part.py
vectara_client/models/corpus.py
vectara_client/models/corpus_custom_dimension.py
vectara_client/models/corpus_limits.py
vectara_client/models/create_api_key_request.py
vectara_client/models/create_app_client_request.py
vectara_client/models/create_client_credentials_request.py
vectara_client/models/create_corpus_request.py
vectara_client/models/create_document_request.py
vectara_client-0.0.10.dist-info/METADATA
vectara_client-0.0.10.dist-info/WHEEL
vectara_client-0.0.10.dist-info/top_level.txt
vectara_client-0.0.10.dist-info/RECORD
