Metadata-Version: 2.1
Name: vectara_client
Version: 0.0.10
Summary: Vectara REST API v2
Home-page: https://github.com/david-vectara/vectara-sdk
Author: david@vectara.com
Author-email: feedback@vectara.com
License: Apache-2.0
Keywords: OpenAPI,OpenAPI-Generator,Vectara REST API v2
Classifier: Development Status :: 2 - Pre-Alpha
Classifier: Environment :: Console
Classifier: License :: OSI Approved :: GNU Affero General Public License v3 or later (AGPLv3+)
Classifier: Natural Language :: English
Classifier: Programming Language :: Python :: 3 :: Only
Classifier: Programming Language :: Python :: 3.12
Classifier: Topic :: Utilities
Requires-Python: >=3.12
Requires-Dist: urllib3 <2.1.0,>=1.25.3
Requires-Dist: python-dateutil
Requires-Dist: pydantic >=2
Requires-Dist: typing-extensions >=4.7.1
Requires-Dist: requests >=2.31.0
Requires-Dist: Authlib >=1.3.1
Requires-Dist: pyaml ==23.9.7
Requires-Dist: dacite ==1.8.1
Requires-Dist: tqdm ==4.66.1
Requires-Dist: requests-toolbelt ==1.0.0
Requires-Dist: cryptography ==40.0.2
